verilog/linebuffer_3x3.v
// linebuffer_3x3.v -- Verilog-2001 compatible
// Sliding 3x3 window generator for convolution
// Works for streaming single-channel image input

module linebuffer_3x3 #
(
    parameter DATA_W = 8,
    parameter IMG_W  = 8     // width of image row (number of pixels per line)
)
(
    input  wire                     clk,
    input  wire                     rst,
    input  wire                     in_valid,
    input  wire signed [DATA_W-1:0] pixel_in,

    output reg                      out_valid,
    output reg signed [DATA_W-1:0]  p00, p01, p02,
    output reg signed [DATA_W-1:0]  p10, p11, p12,
    output reg signed [DATA_W-1:0]  p20, p21, p22
);

    // Two line buffers to store the last two rows
    reg signed [DATA_W-1:0] line1 [0:IMG_W-1];
    reg signed [DATA_W-1:0] line2 [0:IMG_W-1];
    integer i;

    reg [15:0] col; // column counter

    always @(posedge clk) begin
        if (rst) begin
            for (i=0; i<IMG_W; i=i+1) begin
                line1[i] <= 0;
                line2[i] <= 0;
            end
            col <= 0;
            out_valid <= 0;

            p00 <= 0; p01 <= 0; p02 <= 0;
            p10 <= 0; p11 <= 0; p12 <= 0;
            p20 <= 0; p21 <= 0; p22 <= 0;
        end
        else if (in_valid) begin
            // Shift pixel rows
            line2[col] <= line1[col];
            line1[col] <= pixel_in;

            // After we have at least 2 previous columns
            if (col >= 2) begin
                p00 <= line2[col-2];
                p01 <= line2[col-1];
                p02 <= line2[col];
                p10 <= line1[col-2];
                p11 <= line1[col-1];
                p12 <= line1[col];
                p20 <= 0; // bottom row placeholder until next row arrives
                p21 <= 0;
                p22 <= 0;
                out_valid <= 1'b1;
            end else begin
                out_valid <= 1'b0;
            end

            // Increment column index
            if (col == IMG_W-1)
                col <= 0;
            else
                col <= col + 1;
        end else begin
            out_valid <= 0;
        end
    end
endmodule

tb_linebuffer.v
`timescale 1ns/1ps
module tb_linebuffer;

    reg clk, rst, in_valid;
    reg signed [7:0] pixel_in;
    wire out_valid;
    wire signed [7:0] p00,p01,p02,p10,p11,p12,p20,p21,p22;

    // Instantiate DUT
    linebuffer_3x3 #(.DATA_W(8), .IMG_W(4)) dut (
        .clk(clk), .rst(rst),
        .in_valid(in_valid),
        .pixel_in(pixel_in),
        .out_valid(out_valid),
        .p00(p00),.p01(p01),.p02(p02),
        .p10(p10),.p11(p11),.p12(p12),
        .p20(p20),.p21(p21),.p22(p22)
    );

    initial begin
        $dumpfile("wave_linebuffer.vcd");
        $dumpvars(0, tb_linebuffer);

        clk=0; rst=1; in_valid=0; pixel_in=0;
        #20 rst=0;

        // Feed 8 pixels
        in_valid=1;
        pixel_in=8'd10; #10;
        pixel_in=8'd20; #10;
        pixel_in=8'd30; #10;
        pixel_in=8'd40; #10;
        pixel_in=8'd50; #10;
        pixel_in=8'd60; #10;
        pixel_in=8'd70; #10;
        pixel_in=8'd80; #10;
        in_valid=0;

        #40 $finish;
    end

    always #5 clk=~clk;
endmodule

wave_linebuffer.vcd
$date
	Tue Nov 04 18:26:27 2025
$end
$version
	Icarus Verilog
$end
$timescale
	1ps
$end
$scope module tb_linebuffer $end
$var wire 8 ! p22 [7:0] $end
$var wire 8 " p21 [7:0] $end
$var wire 8 # p20 [7:0] $end
$var wire 8 $ p12 [7:0] $end
$var wire 8 % p11 [7:0] $end
$var wire 8 & p10 [7:0] $end
$var wire 8 ' p02 [7:0] $end
$var wire 8 ( p01 [7:0] $end
$var wire 8 ) p00 [7:0] $end
$var wire 1 * out_valid $end
$var reg 1 + clk $end
$var reg 1 , in_valid $end
$var reg 8 - pixel_in [7:0] $end
$var reg 1 . rst $end
$scope module dut $end
$var wire 1 + clk $end
$var wire 1 , in_valid $end
$var wire 8 / pixel_in [7:0] $end
$var wire 1 . rst $end
$var parameter 32 0 DATA_W $end
$var parameter 32 1 IMG_W $end
$var reg 16 2 col [15:0] $end
$var reg 1 * out_valid $end
$var reg 8 3 p00 [7:0] $end
$var reg 8 4 p01 [7:0] $end
$var reg 8 5 p02 [7:0] $end
$var reg 8 6 p10 [7:0] $end
$var reg 8 7 p11 [7:0] $end
$var reg 8 8 p12 [7:0] $end
$var reg 8 9 p20 [7:0] $end
$var reg 8 : p21 [7:0] $end
$var reg 8 ; p22 [7:0] $end
$var integer 32 < i [31:0] $end
$upscope $end
$upscope $end
$enddefinitions $end
$comment Show the parameter values. $end
$dumpall
b100 1
b1000 0
$end
#0
$dumpvars
bx <
bx ;
bx :
bx 9
bx 8
bx 7
bx 6
bx 5
bx 4
bx 3
bx 2
b0 /
1.
b0 -
0,
0+
x*
bx )
bx (
bx '
bx &
bx %
bx $
bx #
bx "
bx !
$end
#5000
b0 !
b0 ;
b0 "
b0 :
b0 #
b0 9
b0 $
b0 8
b0 %
b0 7
b0 &
b0 6
b0 '
b0 5
b0 (
b0 4
b0 )
b0 3
0*
b0 2
b100 <
1+
#10000
0+
#15000
b100 <
1+
#20000
0+
b1010 -
b1010 /
1,
0.
#25000
b1 2
1+
#30000
0+
b10100 -
b10100 /
#35000
b10 2
1+
#40000
0+
b11110 -
b11110 /
#45000
b11 2
1*
b10100 %
b10100 7
b1010 &
b1010 6
1+
#50000
0+
b101000 -
b101000 /
#55000
b0 2
b11110 %
b11110 7
b10100 &
b10100 6
1+
#60000
0+
b110010 -
b110010 /
#65000
b1 2
0*
1+
#70000
0+
b111100 -
b111100 /
#75000
b10 2
1+
#80000
0+
b1000110 -
b1000110 /
#85000
b11 2
1*
b11110 $
b11110 8
b111100 %
b111100 7
b110010 &
b110010 6
b10100 (
b10100 4
b1010 )
b1010 3
1+
#90000
0+
b1010000 -
b1010000 /
#95000
b0 2
b101000 $
b101000 8
b1000110 %
b1000110 7
b111100 &
b111100 6
b11110 (
b11110 4
b10100 )
b10100 3
1+
#100000
0+
0,
#105000
0*
1+
