batchnorm_scale_shift.v
module batchnorm_scale_shift #
(
    parameter DATA_W = 8,
    parameter FRAC   = 4,
    parameter GAMMA  = (1<<FRAC), // scale (1.0)
    parameter BETA   = 0          // offset
)
(
    input  wire                     clk,
    input  wire                     rst,
    input  wire signed [DATA_W-1:0] in_data,
    input  wire                     in_valid,
    output reg  signed [DATA_W-1:0] out_data,
    output reg                      out_valid
);
    reg signed [DATA_W+7:0] mult, res;

    always @(posedge clk) begin
        if (rst) begin
            out_data  <= 0;
            out_valid <= 0;
        end else begin
            if (in_valid) begin
                mult = in_data * GAMMA;
                res  = (mult >>> FRAC) + BETA;
                out_data <= res[DATA_W-1:0];
                out_valid <= 1'b1;
            end else
                out_valid <= 1'b0;
        end
    end
endmodule

tb_batchnorm.v
`timescale 1ns/1ps
module tb_batchnorm;
    reg clk, rst;
    reg signed [7:0] in_data;
    reg in_valid;
    wire signed [7:0] out_data;
    wire out_valid;

    // gamma=1.5→24, beta=0.25→4
    batchnorm_scale_shift #(.DATA_W(8), .FRAC(4), .GAMMA(24), .BETA(4)) dut (
        .clk(clk), .rst(rst),
        .in_data(in_data), .in_valid(in_valid),
        .out_data(out_data), .out_valid(out_valid)
    );

    initial begin
        $dumpfile("wave_batchnorm.vcd");
        $dumpvars(0, tb_batchnorm);
        clk=0; rst=1; in_valid=0; in_data=0;
        #20 rst=0;

        in_valid=1; in_data=8'd16; #10;
        in_data=-8'd16; #10; in_valid=0;
        #40 $finish;
    end
    always #5 clk=~clk;
endmodule

wave_batchnorm.vcd
$date
	Tue Nov 04 18:02:15 2025
$end
$version
	Icarus Verilog
$end
$timescale
	1ps
$end
$scope module tb_batchnorm $end
$var wire 1 ! out_valid $end
$var wire 8 " out_data [7:0] $end
$var reg 1 # clk $end
$var reg 8 $ in_data [7:0] $end
$var reg 1 % in_valid $end
$var reg 1 & rst $end
$scope module dut $end
$var wire 1 # clk $end
$var wire 8 ' in_data [7:0] $end
$var wire 1 % in_valid $end
$var wire 1 & rst $end
$var parameter 32 ( BETA $end
$var parameter 32 ) DATA_W $end
$var parameter 32 * FRAC $end
$var parameter 32 + GAMMA $end
$var reg 16 , mult [15:0] $end
$var reg 8 - out_data [7:0] $end
$var reg 1 ! out_valid $end
$var reg 16 . res [15:0] $end
$upscope $end
$upscope $end
$enddefinitions $end
$comment Show the parameter values. $end
$dumpall
b11000 +
b100 *
b1000 )
b100 (
$end
#0
$dumpvars
bx .
bx -
bx ,
b0 '
1&
0%
b0 $
0#
bx "
x!
$end
#5000
0!
b0 "
b0 -
1#
#10000
0#
#15000
1#
#20000
0#
b10000 $
b10000 '
1%
0&
#25000
1!
b11100 "
b11100 -
b11100 .
b110000000 ,
1#
#30000
0#
b11110000 $
b11110000 '
#35000
b11101100 "
b11101100 -
b1111111111101100 .
b1111111010000000 ,
1#
#40000
0#
0%
#45000
0!
1#
