verilog/maxpool2x2.v
// maxpool2x2.v - Verilog-2001
// Non-overlapping 2x2 maxpool.
// All ports plain Verilog-2001, inputs/outputs declared signed so comparisons are signed.

module maxpool2x2 #
(
    parameter DATA_W = 8
)
(
    input  wire                     clk,
    input  wire                     rst,
    input  wire                     in_valid,
    input  wire signed [DATA_W-1:0] p00,
    input  wire signed [DATA_W-1:0] p01,
    input  wire signed [DATA_W-1:0] p10,
    input  wire signed [DATA_W-1:0] p11,
    output reg  signed [DATA_W-1:0] out_data,
    output reg                      out_valid
);

    reg signed [DATA_W-1:0] max1;
    reg signed [DATA_W-1:0] max2;

    always @(posedge clk) begin
        if (rst) begin
            out_valid <= 1'b0;
            out_data  <= {DATA_W{1'b0}};
            max1 <= {DATA_W{1'b0}};
            max2 <= {DATA_W{1'b0}};
        end else begin
            if (in_valid) begin
                // compute pairwise maxima (signed comparison)
                if (p00 > p01) max1 <= p00;
                else           max1 <= p01;

                if (p10 > p11) max2 <= p10;
                else           max2 <= p11;

                // choose final max
                if ( (p00 > p01 ? p00 : p01) > (p10 > p11 ? p10 : p11) )
                    out_data <= (p00 > p01 ? p00 : p01);
                else
                    out_data <= (p10 > p11 ? p10 : p11);

                out_valid <= 1'b1;
            end else begin
                out_valid <= 1'b0;
            end
        end
    end

endmodule

linebuffer_2x2.v
// linebuffer_2x2.v
// Verilog-2001 : generates 2×2 window from pixel stream (for pooling)
module linebuffer_2x2 #
(
    parameter DATA_W = 8,
    parameter IMG_W  = 8
)
(
    input  wire                     clk,
    input  wire                     rst,
    input  wire                     in_valid,
    input  wire signed [DATA_W-1:0] pixel_in,

    output reg                      out_valid,
    output reg signed [DATA_W-1:0]  p00, p01,
    output reg signed [DATA_W-1:0]  p10, p11
);

    // shift register for previous row
    reg signed [DATA_W-1:0] linebuf [0:IMG_W-1];
    integer i;
    reg [15:0] col;
    reg row_valid;

    always @(posedge clk) begin
        if (rst) begin
            col <= 0;
            out_valid <= 0;
            row_valid <= 0;
            for (i=0;i<IMG_W;i=i+1)
                linebuf[i] <= 0;
        end else if (in_valid) begin
            // shift pixels in current row
            if (col < IMG_W)
                col <= col + 1;
            else
                col <= 1;

            // form 2×2 window when at least 2 rows and 2 cols available
            if (row_valid && col >= 2) begin
                p00 <= linebuf[col-2];
                p01 <= linebuf[col-1];
                p10 <= pixel_in;
                p11 <= pixel_in; // placeholder until next pixel arrives
                out_valid <= 1;
            end else begin
                out_valid <= 0;
            end

            // update line buffer with current pixel (stores previous row)
            linebuf[col-1] <= pixel_in;
        end else begin
            out_valid <= 0;
        end
    end

    // mark after first row complete
    always @(posedge clk) begin
        if (rst)
            row_valid <= 0;
        else if (in_valid && col == IMG_W)
            row_valid <= 1;
    end
endmodule

leaky_relu.v
// leaky_relu.v  --  plain Verilog-2001
module leaky_relu #
(
    parameter DATA_W = 8,
    parameter FRAC   = 4,
    parameter A_NUM  = 1,
    parameter A_DEN  = 4
)
(
    input  wire                     clk,
    input  wire                     rst,
    input  wire signed [DATA_W-1:0] in_data,
    input  wire                     in_valid,
    output reg  signed [DATA_W-1:0] out_data,
    output reg                      out_valid
);

    // wider product to hold multiply result
    reg signed [DATA_W+7:0] prod;
    reg signed [DATA_W+7:0] scaled;   // holds shifted / divided value

    always @(posedge clk) begin
        if (rst) begin
            out_data  <= 0;
            out_valid <= 0;
        end
        else begin
            if (in_valid) begin
                if (in_data[DATA_W-1] == 1'b0) begin
                    // positive input → passthrough
                    out_data <= in_data;
                end
                else begin
                    // negative input → scale by alpha = A_NUM / A_DEN
                    prod = in_data * A_NUM;

                    // choose divide amount
                    if (A_DEN == 1)
                        scaled = prod;
                    else if (A_DEN == 2)
                        scaled = prod >>> 1;
                    else if (A_DEN == 4)
                        scaled = prod >>> 2;
                    else
                        scaled = prod / A_DEN;

                    // take lower DATA_W bits for output
                    out_data <= scaled[DATA_W-1:0];
                end
                out_valid <= 1'b1;
            end
            else begin
                out_valid <= 1'b0;
            end
        end
    end
endmodule

batchnorm_scale_shift.v
module batchnorm_scale_shift #
(
    parameter DATA_W = 8,
    parameter FRAC   = 4,
    parameter GAMMA  = (1<<FRAC), // scale (1.0)
    parameter BETA   = 0          // offset
)
(
    input  wire                     clk,
    input  wire                     rst,
    input  wire signed [DATA_W-1:0] in_data,
    input  wire                     in_valid,
    output reg  signed [DATA_W-1:0] out_data,
    output reg                      out_valid
);
    reg signed [DATA_W+7:0] mult, res;

    always @(posedge clk) begin
        if (rst) begin
            out_data  <= 0;
            out_valid <= 0;
        end else begin
            if (in_valid) begin
                mult = in_data * GAMMA;
                res  = (mult >>> FRAC) + BETA;
                out_data <= res[DATA_W-1:0];
                out_valid <= 1'b1;
            end else
                out_valid <= 1'b0;
        end
    end
endmodule

verilog/conv3x3_single_ch.v
module conv3x3_single_ch #
(
    parameter DATA_W = 8,
    parameter FRAC   = 4,
    parameter W00=0,parameter W01=0,parameter W02=0,
    parameter W10=0,parameter W11=0,parameter W12=0,
    parameter W20=0,parameter W21=0,parameter W22=0,
    parameter BIAS=0
)
(
    input  wire                     clk,
    input  wire                     rst,
    input  wire                     in_valid,
    input  wire signed [DATA_W-1:0] p00,p01,p02,p10,p11,p12,p20,p21,p22,
    output reg  signed [DATA_W-1:0] out_data,
    output reg                      out_valid
);
    reg signed [DATA_W+12:0] acc;
    reg signed [DATA_W+7:0]  prod;

    always @(posedge clk) begin
        if (rst) begin
            out_valid<=0; out_data<=0;
        end else if (in_valid) begin
            acc=0;
            prod=p00*W00; acc=acc+prod;
            prod=p01*W01; acc=acc+prod;
            prod=p02*W02; acc=acc+prod;
            prod=p10*W10; acc=acc+prod;
            prod=p11*W11; acc=acc+prod;
            prod=p12*W12; acc=acc+prod;
            prod=p20*W20; acc=acc+prod;
            prod=p21*W21; acc=acc+prod;
            prod=p22*W22; acc=acc+prod;
            acc=acc+(BIAS<<<FRAC);
            out_data<=acc>>>FRAC;
            out_valid<=1;
        end else
            out_valid<=0;
    end
endmodule

verilog/linebuffer_3x3.v
// linebuffer_3x3.v -- Verilog-2001 compatible
// Sliding 3x3 window generator for convolution
// Works for streaming single-channel image input

module linebuffer_3x3 #
(
    parameter DATA_W = 8,
    parameter IMG_W  = 8     // width of image row (number of pixels per line)
)
(
    input  wire                     clk,
    input  wire                     rst,
    input  wire                     in_valid,
    input  wire signed [DATA_W-1:0] pixel_in,

    output reg                      out_valid,
    output reg signed [DATA_W-1:0]  p00, p01, p02,
    output reg signed [DATA_W-1:0]  p10, p11, p12,
    output reg signed [DATA_W-1:0]  p20, p21, p22
);

    // Two line buffers to store the last two rows
    reg signed [DATA_W-1:0] line1 [0:IMG_W-1];
    reg signed [DATA_W-1:0] line2 [0:IMG_W-1];
    integer i;

    reg [15:0] col; // column counter

    always @(posedge clk) begin
        if (rst) begin
            for (i=0; i<IMG_W; i=i+1) begin
                line1[i] <= 0;
                line2[i] <= 0;
            end
            col <= 0;
            out_valid <= 0;

            p00 <= 0; p01 <= 0; p02 <= 0;
            p10 <= 0; p11 <= 0; p12 <= 0;
            p20 <= 0; p21 <= 0; p22 <= 0;
        end
        else if (in_valid) begin
            // Shift pixel rows
            line2[col] <= line1[col];
            line1[col] <= pixel_in;

            // After we have at least 2 previous columns
            if (col >= 2) begin
                p00 <= line2[col-2];
                p01 <= line2[col-1];
                p02 <= line2[col];
                p10 <= line1[col-2];
                p11 <= line1[col-1];
                p12 <= line1[col];
                p20 <= 0; // bottom row placeholder until next row arrives
                p21 <= 0;
                p22 <= 0;
                out_valid <= 1'b1;
            end else begin
                out_valid <= 1'b0;
            end

            // Increment column index
            if (col == IMG_W-1)
                col <= 0;
            else
                col <= col + 1;
        end else begin
            out_valid <= 0;
        end
    end
endmodule

cnn_top_with_pool.v
// cnn_top_with_pool.v
// Verilog-2001 top-level CNN pipeline with true 2x2 maxpooling
// pipeline: pixel_stream -> linebuffer_3x3 -> conv3x3 -> batchnorm -> leaky_relu -> linebuffer_2x2 -> maxpool2x2

module cnn_top_with_pool #
(
    parameter DATA_W = 8,
    parameter FRAC   = 4,
    parameter IMG_W  = 8
)
(
    input  wire                     clk,
    input  wire                     rst,
    input  wire                     in_valid,
    input  wire signed [DATA_W-1:0] pixel_in,

    output reg                      out_valid,
    output reg signed [DATA_W-1:0]  out_data
);

    // ---------------- Line Buffer (3x3 for Conv) ----------------
    wire lb_valid;
    wire signed [DATA_W-1:0] p00,p01,p02,p10,p11,p12,p20,p21,p22;

    linebuffer_3x3 #(.DATA_W(DATA_W), .IMG_W(IMG_W)) lb (
        .clk(clk), .rst(rst),
        .in_valid(in_valid), .pixel_in(pixel_in),
        .out_valid(lb_valid),
        .p00(p00),.p01(p01),.p02(p02),
        .p10(p10),.p11(p11),.p12(p12),
        .p20(p20),.p21(p21),.p22(p22)
    );

    // ---------------- Convolution ----------------
    reg conv_in_valid;
    wire conv_out_valid;
    wire signed [DATA_W-1:0] conv_out_data;

    conv3x3_single_ch #(
        .DATA_W(DATA_W), .FRAC(FRAC),
        .W00(0),  .W01(-16), .W02(0),
        .W10(-16),.W11(64),  .W12(-16),
        .W20(0),  .W21(-16), .W22(0),
        .BIAS(0)
    ) conv (
        .clk(clk), .rst(rst), .in_valid(conv_in_valid),
        .p00(p00),.p01(p01),.p02(p02),
        .p10(p10),.p11(p11),.p12(p12),
        .p20(p20),.p21(p21),.p22(p22),
        .out_data(conv_out_data), .out_valid(conv_out_valid)
    );

    // ---------------- BatchNorm ----------------
    reg bn_in_valid;
    wire bn_out_valid;
    wire signed [DATA_W-1:0] bn_out_data;

    batchnorm_scale_shift #(
        .DATA_W(DATA_W), .FRAC(FRAC),
        .GAMMA(24), .BETA(4)
    ) bn (
        .clk(clk), .rst(rst),
        .in_data(conv_out_data), .in_valid(bn_in_valid),
        .out_data(bn_out_data), .out_valid(bn_out_valid)
    );

    // ---------------- Leaky ReLU ----------------
    reg relu_in_valid;
    wire relu_out_valid;
    wire signed [DATA_W-1:0] relu_out_data;

    leaky_relu #(
        .DATA_W(DATA_W), .FRAC(FRAC),
        .A_NUM(1), .A_DEN(4)
    ) lrelu (
        .clk(clk), .rst(rst),
        .in_data(bn_out_data), .in_valid(relu_in_valid),
        .out_data(relu_out_data), .out_valid(relu_out_valid)
    );

    // ---------------- LineBuffer (2x2 for Pooling) ----------------
    wire lb2_valid;
    wire signed [DATA_W-1:0] pb00,pb01,pb10,pb11;

    linebuffer_2x2 #(.DATA_W(DATA_W), .IMG_W(IMG_W)) pool_lb (
        .clk(clk), .rst(rst),
        .in_valid(relu_out_valid),
        .pixel_in(relu_out_data),
        .out_valid(lb2_valid),
        .p00(pb00), .p01(pb01),
        .p10(pb10), .p11(pb11)
    );

    // ---------------- MaxPool 2x2 (real spatial pooling) ----------------
    reg pool_in_valid;
    wire pool_out_valid;
    wire signed [DATA_W-1:0] pool_out_data;

    maxpool2x2 #(.DATA_W(DATA_W)) pool (
        .clk(clk), .rst(rst),
        .in_valid(pool_in_valid),
        .p00(pb00), .p01(pb01),
        .p10(pb10), .p11(pb11),
        .out_data(pool_out_data), .out_valid(pool_out_valid)
    );

    // ---------------- Handshake / control pipeline ----------------
    always @(posedge clk) begin
        if (rst) begin
            conv_in_valid <= 0;
            bn_in_valid   <= 0;
            relu_in_valid <= 0;
            pool_in_valid <= 0;
            out_valid     <= 0;
            out_data      <= 0;
        end else begin
            conv_in_valid <= lb_valid;
            bn_in_valid   <= conv_out_valid;
            relu_in_valid <= bn_out_valid;
            pool_in_valid <= lb2_valid;

            if (pool_out_valid) begin
                out_valid <= 1'b1;
                out_data  <= pool_out_data;
            end else begin
                out_valid <= 1'b0;
            end
        end
    end
endmodule

tb_cnn_top_with_pool.v
`timescale 1ns/1ps
module tb_cnn_top_with_pool;

    parameter DATA_W = 8;
    parameter FRAC   = 4;
    parameter IMG_W  = 4;

    reg clk, rst;
    reg in_valid;
    reg signed [DATA_W-1:0] pixel_in;
    wire out_valid;
    wire signed [DATA_W-1:0] out_data;

    cnn_top_with_pool #(.DATA_W(DATA_W), .FRAC(FRAC), .IMG_W(IMG_W)) dut (
        .clk(clk), .rst(rst),
        .in_valid(in_valid),
        .pixel_in(pixel_in),
        .out_valid(out_valid),
        .out_data(out_data)
    );

    initial begin
        $dumpfile("wave_cnn_with_pool.vcd");
        $dumpvars(0, tb_cnn_top_with_pool);
        clk=0; rst=1; in_valid=0; pixel_in=0;
        #20 rst=0;

        // Feed small 2x4 image (Q4 scaled)
        in_valid=1;
        pixel_in=8'd10; #10;
        pixel_in=8'd20; #10;
        pixel_in=8'd30; #10;
        pixel_in=8'd40; #10;
        pixel_in=8'd50; #10;
        pixel_in=8'd60; #10;
        pixel_in=8'd70; #10;
        pixel_in=8'd80; #10;
        in_valid=0;
        #100 $finish;
    end

    always #5 clk = ~clk;
endmodule

wave_cnn_with_pool.vcd
$date
	Tue Nov 04 22:02:08 2025
$end
$version
	Icarus Verilog
$end
$timescale
	1ps
$end
$scope module tb_cnn_top_with_pool $end
$var wire 1 ! out_valid $end
$var wire 8 " out_data [7:0] $end
$var parameter 32 # DATA_W $end
$var parameter 32 $ FRAC $end
$var parameter 32 % IMG_W $end
$var reg 1 & clk $end
$var reg 1 ' in_valid $end
$var reg 8 ( pixel_in [7:0] $end
$var reg 1 ) rst $end
$scope module dut $end
$var wire 1 & clk $end
$var wire 1 ' in_valid $end
$var wire 8 * pixel_in [7:0] $end
$var wire 1 ) rst $end
$var wire 1 + relu_out_valid $end
$var wire 8 , relu_out_data [7:0] $end
$var wire 1 - pool_out_valid $end
$var wire 8 . pool_out_data [7:0] $end
$var wire 8 / pb11 [7:0] $end
$var wire 8 0 pb10 [7:0] $end
$var wire 8 1 pb01 [7:0] $end
$var wire 8 2 pb00 [7:0] $end
$var wire 8 3 p22 [7:0] $end
$var wire 8 4 p21 [7:0] $end
$var wire 8 5 p20 [7:0] $end
$var wire 8 6 p12 [7:0] $end
$var wire 8 7 p11 [7:0] $end
$var wire 8 8 p10 [7:0] $end
$var wire 8 9 p02 [7:0] $end
$var wire 8 : p01 [7:0] $end
$var wire 8 ; p00 [7:0] $end
$var wire 1 < lb_valid $end
$var wire 1 = lb2_valid $end
$var wire 1 > conv_out_valid $end
$var wire 8 ? conv_out_data [7:0] $end
$var wire 1 @ bn_out_valid $end
$var wire 8 A bn_out_data [7:0] $end
$var parameter 32 B DATA_W $end
$var parameter 32 C FRAC $end
$var parameter 32 D IMG_W $end
$var reg 1 E bn_in_valid $end
$var reg 1 F conv_in_valid $end
$var reg 8 G out_data [7:0] $end
$var reg 1 ! out_valid $end
$var reg 1 H pool_in_valid $end
$var reg 1 I relu_in_valid $end
$scope module bn $end
$var wire 1 & clk $end
$var wire 1 E in_valid $end
$var wire 1 ) rst $end
$var wire 8 J in_data [7:0] $end
$var parameter 32 K BETA $end
$var parameter 32 L DATA_W $end
$var parameter 32 M FRAC $end
$var parameter 32 N GAMMA $end
$var reg 16 O mult [15:0] $end
$var reg 8 P out_data [7:0] $end
$var reg 1 @ out_valid $end
$var reg 16 Q res [15:0] $end
$upscope $end
$scope module conv $end
$var wire 1 & clk $end
$var wire 1 F in_valid $end
$var wire 1 ) rst $end
$var wire 8 R p22 [7:0] $end
$var wire 8 S p21 [7:0] $end
$var wire 8 T p20 [7:0] $end
$var wire 8 U p12 [7:0] $end
$var wire 8 V p11 [7:0] $end
$var wire 8 W p10 [7:0] $end
$var wire 8 X p02 [7:0] $end
$var wire 8 Y p01 [7:0] $end
$var wire 8 Z p00 [7:0] $end
$var parameter 32 [ BIAS $end
$var parameter 32 \ DATA_W $end
$var parameter 32 ] FRAC $end
$var parameter 32 ^ W00 $end
$var parameter 32 _ W01 $end
$var parameter 32 ` W02 $end
$var parameter 32 a W10 $end
$var parameter 32 b W11 $end
$var parameter 32 c W12 $end
$var parameter 32 d W20 $end
$var parameter 32 e W21 $end
$var parameter 32 f W22 $end
$var reg 21 g acc [20:0] $end
$var reg 8 h out_data [7:0] $end
$var reg 1 > out_valid $end
$var reg 16 i prod [15:0] $end
$upscope $end
$scope module lb $end
$var wire 1 & clk $end
$var wire 1 ' in_valid $end
$var wire 8 j pixel_in [7:0] $end
$var wire 1 ) rst $end
$var parameter 32 k DATA_W $end
$var parameter 32 l IMG_W $end
$var reg 16 m col [15:0] $end
$var reg 1 < out_valid $end
$var reg 8 n p00 [7:0] $end
$var reg 8 o p01 [7:0] $end
$var reg 8 p p02 [7:0] $end
$var reg 8 q p10 [7:0] $end
$var reg 8 r p11 [7:0] $end
$var reg 8 s p12 [7:0] $end
$var reg 8 t p20 [7:0] $end
$var reg 8 u p21 [7:0] $end
$var reg 8 v p22 [7:0] $end
$var integer 32 w i [31:0] $end
$upscope $end
$scope module lrelu $end
$var wire 1 & clk $end
$var wire 8 x in_data [7:0] $end
$var wire 1 I in_valid $end
$var wire 1 ) rst $end
$var parameter 32 y A_DEN $end
$var parameter 32 z A_NUM $end
$var parameter 32 { DATA_W $end
$var parameter 32 | FRAC $end
$var reg 8 } out_data [7:0] $end
$var reg 1 + out_valid $end
$var reg 16 ~ prod [15:0] $end
$var reg 16 !" scaled [15:0] $end
$upscope $end
$scope module pool $end
$var wire 1 & clk $end
$var wire 1 H in_valid $end
$var wire 1 ) rst $end
$var wire 8 "" p11 [7:0] $end
$var wire 8 #" p10 [7:0] $end
$var wire 8 $" p01 [7:0] $end
$var wire 8 %" p00 [7:0] $end
$var parameter 32 &" DATA_W $end
$var reg 8 '" max1 [7:0] $end
$var reg 8 (" max2 [7:0] $end
$var reg 8 )" out_data [7:0] $end
$var reg 1 - out_valid $end
$upscope $end
$scope module pool_lb $end
$var wire 1 & clk $end
$var wire 1 + in_valid $end
$var wire 8 *" pixel_in [7:0] $end
$var wire 1 ) rst $end
$var parameter 32 +" DATA_W $end
$var parameter 32 ," IMG_W $end
$var reg 16 -" col [15:0] $end
$var reg 1 = out_valid $end
$var reg 8 ." p00 [7:0] $end
$var reg 8 /" p01 [7:0] $end
$var reg 8 0" p10 [7:0] $end
$var reg 8 1" p11 [7:0] $end
$var reg 1 2" row_valid $end
$var integer 32 3" i [31:0] $end
$upscope $end
$upscope $end
$upscope $end
$enddefinitions $end
$comment Show the parameter values. $end
$dumpall
b100 ,"
b1000 +"
b1000 &"
b100 |
b1000 {
b1 z
b100 y
b100 l
b1000 k
b0 f
b11111111111111111111111111110000 e
b0 d
b11111111111111111111111111110000 c
b1000000 b
b11111111111111111111111111110000 a
b0 `
b11111111111111111111111111110000 _
b0 ^
b100 ]
b1000 \
b0 [
b11000 N
b100 M
b1000 L
b100 K
b100 D
b100 C
b1000 B
b100 %
b100 $
b1000 #
$end
#0
$dumpvars
bx 3"
x2"
bx 1"
bx 0"
bx /"
bx ."
bx -"
bx *"
bx )"
bx ("
bx '"
bx %"
bx $"
bx #"
bx ""
bx !"
bx ~
bx }
bx x
bx w
bx v
bx u
bx t
bx s
bx r
bx q
bx p
bx o
bx n
bx m
b0 j
bx i
bx h
bx g
bx Z
bx Y
bx X
bx W
bx V
bx U
bx T
bx S
bx R
bx Q
bx P
bx O
bx J
xI
xH
bx G
xF
xE
bx A
x@
bx ?
x>
x=
x<
bx ;
bx :
bx 9
bx 8
bx 7
bx 6
bx 5
bx 4
bx 3
bx 2
bx 1
bx 0
bx /
bx .
x-
bx ,
x+
b0 *
1)
b0 (
0'
0&
bx "
x!
$end
#5000
b0 3
b0 R
b0 v
b0 4
b0 S
b0 u
b0 5
b0 T
b0 t
b0 6
b0 U
b0 s
b0 7
b0 V
b0 r
b0 8
b0 W
b0 q
b0 9
b0 X
b0 p
b0 :
b0 Y
b0 o
b0 ;
b0 Z
b0 n
0<
b0 m
b0 ?
b0 J
b0 h
0>
0@
b0 A
b0 P
b0 x
0+
b0 ,
b0 }
b0 *"
0=
b0 -"
02"
b0 ("
b0 '"
b0 .
b0 )"
0-
b0 "
b0 G
0!
0H
0I
0E
0F
b100 w
b100 3"
1&
#10000
0&
#15000
b100 3"
b100 w
1&
#20000
0&
b1010 (
b1010 *
b1010 j
1'
0)
#25000
b1 m
1&
#30000
0&
b10100 (
b10100 *
b10100 j
#35000
b10 m
1&
#40000
0&
b11110 (
b11110 *
b11110 j
#45000
b11 m
1<
b10100 7
b10100 V
b10100 r
b1010 8
b1010 W
b1010 q
1&
#50000
0&
b101000 (
b101000 *
b101000 j
#55000
1F
b0 m
b11110 7
b11110 V
b11110 r
b10100 8
b10100 W
b10100 q
1&
#60000
0&
b110010 (
b110010 *
b110010 j
#65000
b1 m
0<
1>
b1100100 ?
b1100100 J
b1100100 h
b0 i
b11001000000 g
1&
#70000
0&
b111100 (
b111100 *
b111100 j
#75000
1E
0F
b10 m
b0 i
b11001000000 g
1&
#80000
0&
b1000110 (
b1000110 *
b1000110 j
#85000
b11 m
1<
b11110 6
b11110 U
b11110 s
b111100 7
b111100 V
b111100 r
b110010 8
b110010 W
b110010 q
b10100 :
b10100 Y
b10100 o
b1010 ;
b1010 Z
b1010 n
0>
1@
b10011010 A
b10011010 P
b10011010 x
b10011010 Q
b100101100000 O
1&
#90000
0&
b1010000 (
b1010000 *
b1010000 j
#95000
1I
0E
1F
b0 m
b101000 6
b101000 U
b101000 s
b1000110 7
b1000110 V
b1000110 r
b111100 8
b111100 W
b111100 q
b11110 :
b11110 Y
b11110 o
b10100 ;
b10100 Z
b10100 n
1&
#100000
0&
0'
#105000
0<
1>
b10010110 ?
b10010110 J
b10010110 h
0@
1+
b11100110 ,
b11100110 }
b11100110 *"
b0 i
b100101100000 g
b1111111111100110 !"
b1111111110011010 ~
1&
#110000
0&
#115000
0I
1E
0F
b1 -"
b0 i
b100101100000 g
1&
#120000
0&
#125000
0>
1@
b1100101 A
b1100101 P
b1100101 x
0+
b10 -"
b1111111101100101 Q
b1111011000010000 O
1&
#130000
0&
#135000
1I
0E
1&
#140000
0&
#145000
0@
1+
b1100101 ,
b1100101 }
b1100101 *"
1&
#150000
0&
#155000
0I
b11 -"
1&
#160000
0&
#165000
0+
b100 -"
1&
