verilog/maxpool2x2.v
// maxpool2x2.v - Verilog-2001
// Non-overlapping 2x2 maxpool.
// All ports plain Verilog-2001, inputs/outputs declared signed so comparisons are signed.

module maxpool2x2 #
(
    parameter DATA_W = 8
)
(
    input  wire                     clk,
    input  wire                     rst,
    input  wire                     in_valid,
    input  wire signed [DATA_W-1:0] p00,
    input  wire signed [DATA_W-1:0] p01,
    input  wire signed [DATA_W-1:0] p10,
    input  wire signed [DATA_W-1:0] p11,
    output reg  signed [DATA_W-1:0] out_data,
    output reg                      out_valid
);

    reg signed [DATA_W-1:0] max1;
    reg signed [DATA_W-1:0] max2;

    always @(posedge clk) begin
        if (rst) begin
            out_valid <= 1'b0;
            out_data  <= {DATA_W{1'b0}};
            max1 <= {DATA_W{1'b0}};
            max2 <= {DATA_W{1'b0}};
        end else begin
            if (in_valid) begin
                // compute pairwise maxima (signed comparison)
                if (p00 > p01) max1 <= p00;
                else           max1 <= p01;

                if (p10 > p11) max2 <= p10;
                else           max2 <= p11;

                // choose final max
                if ( (p00 > p01 ? p00 : p01) > (p10 > p11 ? p10 : p11) )
                    out_data <= (p00 > p01 ? p00 : p01);
                else
                    out_data <= (p10 > p11 ? p10 : p11);

                out_valid <= 1'b1;
            end else begin
                out_valid <= 1'b0;
            end
        end
    end

endmodule

tb_maxpool2x2.v
`timescale 1ns/1ps
module tb_maxpool2x2;
    parameter DATA_W = 8;

    reg clk;
    reg rst;
    reg in_valid;
    reg signed [DATA_W-1:0] p00, p01, p10, p11;
    wire signed [DATA_W-1:0] out_data;
    wire out_valid;

    // Instantiate DUT
    maxpool2x2 #(.DATA_W(DATA_W)) dut (
        .clk(clk),
        .rst(rst),
        .in_valid(in_valid),
        .p00(p00), .p01(p01), .p10(p10), .p11(p11),
        .out_data(out_data),
        .out_valid(out_valid)
    );

    initial begin
        $dumpfile("wave_maxpool2x2.vcd");
        $dumpvars(0, tb_maxpool2x2);

        // init
        clk = 0;
        rst = 1;
        in_valid = 0;
        p00 = 0; p01 = 0; p10 = 0; p11 = 0;

        #20 rst = 0;

        // test 1: positives
        p00 = 8'd5;  p01 = 8'd9;  p10 = 8'd2;  p11 = 8'd7;
        in_valid = 1; #10;  // one cycle of valid input
        in_valid = 0; #10;

        // test 2: negatives (signed)
        p00 = -8'd8; p01 = -8'd5; p10 = -8'd10; p11 = -8'd3;
        in_valid = 1; #10;
        in_valid = 0; #10;

        // test 3: equal values
        p00 = 8'd12; p01 = 8'd12; p10 = 8'd11; p11 = 8'd13;
        in_valid = 1; #10;
        in_valid = 0; #20;

        #50 $finish;
    end

    // simple clock
    always #5 clk = ~clk;

endmodule

wave_maxpool2x2.vcd
$date
	Tue Nov 04 18:10:12 2025
$end
$version
	Icarus Verilog
$end
$timescale
	1ps
$end
$scope module tb_maxpool2x2 $end
$var wire 1 ! out_valid $end
$var wire 8 " out_data [7:0] $end
$var parameter 32 # DATA_W $end
$var reg 1 $ clk $end
$var reg 1 % in_valid $end
$var reg 8 & p00 [7:0] $end
$var reg 8 ' p01 [7:0] $end
$var reg 8 ( p10 [7:0] $end
$var reg 8 ) p11 [7:0] $end
$var reg 1 * rst $end
$scope module dut $end
$var wire 1 $ clk $end
$var wire 1 % in_valid $end
$var wire 8 + p00 [7:0] $end
$var wire 8 , p01 [7:0] $end
$var wire 8 - p10 [7:0] $end
$var wire 8 . p11 [7:0] $end
$var wire 1 * rst $end
$var parameter 32 / DATA_W $end
$var reg 8 0 max1 [7:0] $end
$var reg 8 1 max2 [7:0] $end
$var reg 8 2 out_data [7:0] $end
$var reg 1 ! out_valid $end
$upscope $end
$upscope $end
$enddefinitions $end
$comment Show the parameter values. $end
$dumpall
b1000 /
b1000 #
$end
#0
$dumpvars
bx 2
bx 1
bx 0
b0 .
b0 -
b0 ,
b0 +
1*
b0 )
b0 (
b0 '
b0 &
0%
0$
bx "
x!
$end
#5000
b0 1
b0 0
b0 "
b0 2
0!
1$
#10000
0$
#15000
1$
#20000
0$
1%
b111 )
b111 .
b10 (
b10 -
b1001 '
b1001 ,
b101 &
b101 +
0*
#25000
1!
b1001 "
b1001 2
b111 1
b1001 0
1$
#30000
0$
0%
#35000
0!
1$
#40000
0$
1%
b11111101 )
b11111101 .
b11110110 (
b11110110 -
b11111011 '
b11111011 ,
b11111000 &
b11111000 +
#45000
1!
b11111101 "
b11111101 2
b11111101 1
b11111011 0
1$
#50000
0$
0%
#55000
0!
1$
#60000
0$
1%
b1101 )
b1101 .
b1011 (
b1011 -
b1100 '
b1100 ,
b1100 &
b1100 +
#65000
1!
b1101 "
b1101 2
b1101 1
b1100 0
1$
#70000
0$
0%
#75000
0!
1$
