fc_dotprod.v
module fc_dotprod #
(
    parameter DATA_W=8,
    parameter FRAC=4,
    parameter N=8,
    parameter W0=16,W1=32,W2=48,W3=64,W4=80,W5=96,W6=112,W7=128,
    parameter BIAS=0
)
(
    input  wire                     clk,
    input  wire                     rst,
    input  wire                     in_valid,
    input  wire signed [DATA_W-1:0] in_data,
    output reg  signed [DATA_W-1:0] out_data,
    output reg                      out_valid
);
    integer i;
    reg signed [DATA_W+16:0] acc;
    reg signed [DATA_W+7:0]  prod;
    reg [3:0] count;

    function integer get_weight;
        input integer idx;
        begin
            case(idx)
                0:get_weight=W0;1:get_weight=W1;2:get_weight=W2;3:get_weight=W3;
                4:get_weight=W4;5:get_weight=W5;6:get_weight=W6;7:get_weight=W7;
                default:get_weight=0;
            endcase
        end
    endfunction

    always @(posedge clk) begin
        if(rst) begin
            acc<=0;count<=0;out_valid<=0;
        end else begin
            if(in_valid) begin
                prod=in_data*get_weight(count);
                acc=acc+prod;
                count<=count+1;
                out_valid<=0;
            end else if(count!=0) begin
                acc=acc+(BIAS<<<FRAC);
                out_data<=acc>>>FRAC;
                out_valid<=1;
                acc<=0;count<=0;
            end else
                out_valid<=0;
        end
    end
endmodule

tb_fc.v
`timescale 1ns/1ps
module tb_fc;
    reg clk,rst,in_valid;
    reg signed [7:0] in_data;
    wire signed [7:0] out_data;
    wire out_valid;

    fc_dotprod dut(.clk(clk),.rst(rst),.in_valid(in_valid),
                   .in_data(in_data),.out_data(out_data),.out_valid(out_valid));

    integer i;
    initial begin
        $dumpfile("wave_fc.vcd");
        $dumpvars(0,tb_fc);
        clk=0;rst=1;in_valid=0;in_data=0;
        #20 rst=0;
        for(i=0;i<8;i=i+1) begin
            in_data=8'd16;in_valid=1;#10;
        end
        in_valid=0;#40;$finish;
    end
    always #5 clk=~clk;
endmodule

wave_fc.vcd
$date
	Tue Nov 04 18:20:20 2025
$end
$version
	Icarus Verilog
$end
$timescale
	1ps
$end
$scope module tb_fc $end
$var wire 1 ! out_valid $end
$var wire 8 " out_data [7:0] $end
$var reg 1 # clk $end
$var reg 8 $ in_data [7:0] $end
$var reg 1 % in_valid $end
$var reg 1 & rst $end
$var integer 32 ' i [31:0] $end
$scope module dut $end
$var wire 1 # clk $end
$var wire 8 ( in_data [7:0] $end
$var wire 1 % in_valid $end
$var wire 1 & rst $end
$var parameter 32 ) BIAS $end
$var parameter 32 * DATA_W $end
$var parameter 32 + FRAC $end
$var parameter 32 , N $end
$var parameter 32 - W0 $end
$var parameter 32 . W1 $end
$var parameter 32 / W2 $end
$var parameter 32 0 W3 $end
$var parameter 32 1 W4 $end
$var parameter 32 2 W5 $end
$var parameter 32 3 W6 $end
$var parameter 32 4 W7 $end
$var reg 25 5 acc [24:0] $end
$var reg 4 6 count [3:0] $end
$var reg 8 7 out_data [7:0] $end
$var reg 1 ! out_valid $end
$var reg 16 8 prod [15:0] $end
$scope function get_weight $end
$var integer 32 9 idx [31:0] $end
$upscope $end
$upscope $end
$upscope $end
$enddefinitions $end
$comment Show the parameter values. $end
$dumpall
b10000000 4
b1110000 3
b1100000 2
b1010000 1
b1000000 0
b110000 /
b100000 .
b10000 -
b1000 ,
b100 +
b1000 *
b0 )
$end
#0
$dumpvars
bx 9
bx 8
bx 7
bx 6
bx 5
b0 (
bx '
1&
0%
b0 $
0#
bx "
x!
$end
#5000
0!
b0 6
b0 5
1#
#10000
0#
#15000
1#
#20000
0#
1%
b10000 $
b10000 (
b0 '
0&
#25000
b1 6
b100000000 5
b100000000 8
b0 9
1#
#30000
0#
b1 '
#35000
b10 6
b1100000000 5
b1000000000 8
b1 9
1#
#40000
0#
b10 '
#45000
b11 6
b11000000000 5
b1100000000 8
b10 9
1#
#50000
0#
b11 '
#55000
b100 6
b101000000000 5
b10000000000 8
b11 9
1#
#60000
0#
b100 '
#65000
b101 6
b111100000000 5
b10100000000 8
b100 9
1#
#70000
0#
b101 '
#75000
b110 6
b1010100000000 5
b11000000000 8
b101 9
1#
#80000
0#
b110 '
#85000
b111 6
b1110000000000 5
b11100000000 8
b110 9
1#
#90000
0#
b111 '
#95000
b1000 6
b10010000000000 5
b100000000000 8
b111 9
1#
#100000
0#
0%
b1000 '
#105000
b0 6
b0 5
1!
b1000000 "
b1000000 7
1#
#110000
0#
#115000
0!
1#
