verilog/conv3x3_single_ch.v
module conv3x3_single_ch #
(
    parameter DATA_W = 8,
    parameter FRAC   = 4,
    parameter W00=0,parameter W01=0,parameter W02=0,
    parameter W10=0,parameter W11=0,parameter W12=0,
    parameter W20=0,parameter W21=0,parameter W22=0,
    parameter BIAS=0
)
(
    input  wire                     clk,
    input  wire                     rst,
    input  wire                     in_valid,
    input  wire signed [DATA_W-1:0] p00,p01,p02,p10,p11,p12,p20,p21,p22,
    output reg  signed [DATA_W-1:0] out_data,
    output reg                      out_valid
);
    reg signed [DATA_W+12:0] acc;
    reg signed [DATA_W+7:0]  prod;

    always @(posedge clk) begin
        if (rst) begin
            out_valid<=0; out_data<=0;
        end else if (in_valid) begin
            acc=0;
            prod=p00*W00; acc=acc+prod;
            prod=p01*W01; acc=acc+prod;
            prod=p02*W02; acc=acc+prod;
            prod=p10*W10; acc=acc+prod;
            prod=p11*W11; acc=acc+prod;
            prod=p12*W12; acc=acc+prod;
            prod=p20*W20; acc=acc+prod;
            prod=p21*W21; acc=acc+prod;
            prod=p22*W22; acc=acc+prod;
            acc=acc+(BIAS<<<FRAC);
            out_data<=acc>>>FRAC;
            out_valid<=1;
        end else
            out_valid<=0;
    end
endmodule

tb_conv3x3.v
`timescale 1ns/1ps
module tb_conv3x3;
    reg clk,rst,in_valid;
    reg signed [7:0] p00,p01,p02,p10,p11,p12,p20,p21,p22;
    wire signed [7:0] out_data; wire out_valid;

    conv3x3_single_ch #(
        .DATA_W(8),.FRAC(4),
        .W00(0),.W01(-16),.W02(0),
        .W10(-16),.W11(64),.W12(-16),
        .W20(0),.W21(-16),.W22(0),
        .BIAS(0)
    ) dut(.clk(clk),.rst(rst),.in_valid(in_valid),
          .p00(p00),.p01(p01),.p02(p02),
          .p10(p10),.p11(p11),.p12(p12),
          .p20(p20),.p21(p21),.p22(p22),
          .out_data(out_data),.out_valid(out_valid));

    initial begin
        $dumpfile("wave_conv.vcd");
        $dumpvars(0,tb_conv3x3);
        clk=0;rst=1;in_valid=0;
        #20 rst=0;
        p00=8'd16;p01=8'd16;p02=8'd16;
        p10=8'd16;p11=8'd16;p12=8'd16;
        p20=8'd16;p21=8'd16;p22=8'd16;
        in_valid=1;#10;
        p11=8'd64;#10;
        in_valid=0;#40;$finish;
    end
    always #5 clk=~clk;
endmodule

wave_conv.vcd
$date
	Tue Nov 04 18:16:56 2025
$end
$version
	Icarus Verilog
$end
$timescale
	1ps
$end
$scope module tb_conv3x3 $end
$var wire 1 ! out_valid $end
$var wire 8 " out_data [7:0] $end
$var reg 1 # clk $end
$var reg 1 $ in_valid $end
$var reg 8 % p00 [7:0] $end
$var reg 8 & p01 [7:0] $end
$var reg 8 ' p02 [7:0] $end
$var reg 8 ( p10 [7:0] $end
$var reg 8 ) p11 [7:0] $end
$var reg 8 * p12 [7:0] $end
$var reg 8 + p20 [7:0] $end
$var reg 8 , p21 [7:0] $end
$var reg 8 - p22 [7:0] $end
$var reg 1 . rst $end
$scope module dut $end
$var wire 1 # clk $end
$var wire 1 $ in_valid $end
$var wire 8 / p00 [7:0] $end
$var wire 8 0 p01 [7:0] $end
$var wire 8 1 p02 [7:0] $end
$var wire 8 2 p10 [7:0] $end
$var wire 8 3 p11 [7:0] $end
$var wire 8 4 p12 [7:0] $end
$var wire 8 5 p20 [7:0] $end
$var wire 8 6 p21 [7:0] $end
$var wire 8 7 p22 [7:0] $end
$var wire 1 . rst $end
$var parameter 32 8 BIAS $end
$var parameter 32 9 DATA_W $end
$var parameter 32 : FRAC $end
$var parameter 32 ; W00 $end
$var parameter 32 < W01 $end
$var parameter 32 = W02 $end
$var parameter 32 > W10 $end
$var parameter 32 ? W11 $end
$var parameter 32 @ W12 $end
$var parameter 32 A W20 $end
$var parameter 32 B W21 $end
$var parameter 32 C W22 $end
$var reg 21 D acc [20:0] $end
$var reg 8 E out_data [7:0] $end
$var reg 1 ! out_valid $end
$var reg 16 F prod [15:0] $end
$upscope $end
$upscope $end
$enddefinitions $end
$comment Show the parameter values. $end
$dumpall
b0 C
b11111111111111111111111111110000 B
b0 A
b11111111111111111111111111110000 @
b1000000 ?
b11111111111111111111111111110000 >
b0 =
b11111111111111111111111111110000 <
b0 ;
b100 :
b1000 9
b0 8
$end
#0
$dumpvars
bx F
bx E
bx D
bx 7
bx 6
bx 5
bx 4
bx 3
bx 2
bx 1
bx 0
bx /
1.
bx -
bx ,
bx +
bx *
bx )
bx (
bx '
bx &
bx %
0$
0#
bx "
x!
$end
#5000
b0 "
b0 E
0!
1#
#10000
0#
#15000
1#
#20000
0#
1$
b10000 -
b10000 7
b10000 ,
b10000 6
b10000 +
b10000 5
b10000 *
b10000 4
b10000 )
b10000 3
b10000 (
b10000 2
b10000 '
b10000 1
b10000 &
b10000 0
b10000 %
b10000 /
0.
#25000
1!
b0 F
b0 D
1#
#30000
0#
b1000000 )
b1000000 3
#35000
b11000000 "
b11000000 E
b110000000000 D
b0 F
1#
#40000
0#
0$
#45000
0!
1#
