leaky_relu.v
// leaky_relu.v  --  plain Verilog-2001
module leaky_relu #
(
    parameter DATA_W = 8,
    parameter FRAC   = 4,
    parameter A_NUM  = 1,
    parameter A_DEN  = 4
)
(
    input  wire                     clk,
    input  wire                     rst,
    input  wire signed [DATA_W-1:0] in_data,
    input  wire                     in_valid,
    output reg  signed [DATA_W-1:0] out_data,
    output reg                      out_valid
);

    // wider product to hold multiply result
    reg signed [DATA_W+7:0] prod;
    reg signed [DATA_W+7:0] scaled;   // holds shifted / divided value

    always @(posedge clk) begin
        if (rst) begin
            out_data  <= 0;
            out_valid <= 0;
        end
        else begin
            if (in_valid) begin
                if (in_data[DATA_W-1] == 1'b0) begin
                    // positive input → passthrough
                    out_data <= in_data;
                end
                else begin
                    // negative input → scale by alpha = A_NUM / A_DEN
                    prod = in_data * A_NUM;

                    // choose divide amount
                    if (A_DEN == 1)
                        scaled = prod;
                    else if (A_DEN == 2)
                        scaled = prod >>> 1;
                    else if (A_DEN == 4)
                        scaled = prod >>> 2;
                    else
                        scaled = prod / A_DEN;

                    // take lower DATA_W bits for output
                    out_data <= scaled[DATA_W-1:0];
                end
                out_valid <= 1'b1;
            end
            else begin
                out_valid <= 1'b0;
            end
        end
    end
endmodule

tb_leaky_relu.v
`timescale 1ns/1ps
module tb_leaky_relu;
    reg clk, rst;
    reg signed [7:0] in_data;
    reg in_valid;
    wire signed [7:0] out_data;
    wire out_valid;

    leaky_relu #(.DATA_W(8), .FRAC(4), .A_NUM(1), .A_DEN(4)) dut (
        .clk(clk), .rst(rst),
        .in_data(in_data), .in_valid(in_valid),
        .out_data(out_data), .out_valid(out_valid)
    );

    initial begin
        $dumpfile("wave_leaky_relu.vcd");
        $dumpvars(0, tb_leaky_relu);
        clk = 0; rst = 1; in_valid = 0; in_data = 0;
        #20 rst = 0;

        in_valid = 1;
        in_data = 8'd16; #10;   // +1.0
        in_data = 8'd24; #10;   // +1.5
        in_data = -8'd16; #10;  // -1.0
        in_data = -8'd24; #10;  // -1.5
        in_valid = 0;

        #50 $finish;
    end

    always #5 clk = ~clk;
endmodule

wave_leaky_relu.vcd
$date
	Tue Nov 04 17:32:44 2025
$end
$version
	Icarus Verilog
$end
$timescale
	1ps
$end
$scope module tb_leaky_relu $end
$var wire 1 ! out_valid $end
$var wire 8 " out_data [7:0] $end
$var reg 1 # clk $end
$var reg 8 $ in_data [7:0] $end
$var reg 1 % in_valid $end
$var reg 1 & rst $end
$scope module dut $end
$var wire 1 # clk $end
$var wire 8 ' in_data [7:0] $end
$var wire 1 % in_valid $end
$var wire 1 & rst $end
$var parameter 32 ( A_DEN $end
$var parameter 32 ) A_NUM $end
$var parameter 32 * DATA_W $end
$var parameter 32 + FRAC $end
$var reg 8 , out_data [7:0] $end
$var reg 1 ! out_valid $end
$var reg 16 - prod [15:0] $end
$var reg 16 . scaled [15:0] $end
$upscope $end
$upscope $end
$enddefinitions $end
$comment Show the parameter values. $end
$dumpall
b100 +
b1000 *
b1 )
b100 (
$end
#0
$dumpvars
bx .
bx -
bx ,
b0 '
1&
0%
b0 $
0#
bx "
x!
$end
#5000
0!
b0 "
b0 ,
1#
#10000
0#
#15000
1#
#20000
0#
b10000 $
b10000 '
1%
0&
#25000
1!
b10000 "
b10000 ,
1#
#30000
0#
b11000 $
b11000 '
#35000
b11000 "
b11000 ,
1#
#40000
0#
b11110000 $
b11110000 '
#45000
b11111100 "
b11111100 ,
b1111111111111100 .
b1111111111110000 -
1#
#50000
0#
b11101000 $
b11101000 '
#55000
b11111010 "
b11111010 ,
b1111111111111010 .
b1111111111101000 -
1#
#60000
0#
0%
#65000
0!
1#
